mongo_orm/__init__.py
mongo_orm/core.py
mongo_orm/utils.py
mongo_entity_orm-0.1.1.dist-info/LICENSE
mongo_entity_orm-0.1.1.dist-info/METADATA
mongo_entity_orm-0.1.1.dist-info/WHEEL
mongo_entity_orm-0.1.1.dist-info/RECORD
